{
  "allProducts": [
    {
      "id": "8542040",
      "name": "Amaro Alpino",
      "photos": [
        {
          "id": "3114553",
          "url": "https://www.datocms-assets.com/30257/1603407790-packshot-argala-amaro-alpino.png"
        }
      ],
      "variants": [
        {
          "name": "700ml",
          "sku": "BI-AR-AMAL-70"
        }
      ]
    },
    {
      "id": "121440390",
      "name": "Gin al Genepy",
      "photos": [
        {
          "id": "46473323",
          "url": "https://www.datocms-assets.com/30257/1651520894-packshot-argala-liquori-alpini-gin-genepy.png"
        }
      ],
      "variants": [
        {
          "name": "700ml",
          "sku": "GI-AR-GIALGE-70"
        }
      ]
    },
    {
      "id": "9899973",
      "name": "Sepia Amer",
      "photos": [
        {
          "id": "3851879",
          "url": "https://www.datocms-assets.com/30257/1604674323-packshot-audemus-sepia-amer.png"
        }
      ],
      "variants": [
        {
          "name": "500ml",
          "sku": "LI-AUSP-SEAM-50"
        }
      ]
    },
    {
      "id": "113599818",
      "name": "Erika Reinaissance Gin",
      "photos": [
        {
          "id": "46353485",
          "url": "https://www.datocms-assets.com/30257/1650308854-packshot-erika-reinaissance-gin.png"
        }
      ],
      "variants": [
        {
          "name": "500ml",
          "sku": "GI-ER-ERRE-50"
        }
      ]
    },
    {
      "id": "71702315",
      "name": "Pure Single Rum",
      "photos": [
        {
          "id": "30126660",
          "url": "https://www.datocms-assets.com/30257/1636485640-ninefold-pure-single-rum-packshot.png"
        }
      ],
      "variants": [
        {
          "name": "700ml",
          "sku": "RU-NI-PUSIRU-70"
        }
      ]
    },
    {
      "id": "71702516",
      "name": "Dormont Spiced",
      "photos": [
        {
          "id": "30126752",
          "url": "https://www.datocms-assets.com/30257/1636485959-ninefold-dormont-spiced-packshot.png"
        }
      ],
      "variants": [
        {
          "name": "700ml",
          "sku": "RU-NI-DUSPRU-70"
        }
      ]
    },
    {
      "id": "70572444",
      "name": "Baldoria Dry Umami",
      "photos": [
        {
          "id": "29546570",
          "url": "https://www.datocms-assets.com/30257/1636147862-packshot-baldoria-dry-umami.png"
        }
      ],
      "variants": [
        {
          "name": "750ml",
          "sku": "VBUI0075001"
        }
      ]
    },
    {
      "id": "10549778",
      "name": "Erika Dry Gin",
      "photos": [
        {
          "id": "4031249",
          "url": "https://www.datocms-assets.com/30257/1605224831-packshot-erika-dry-gin.png"
        }
      ],
      "variants": [
        {
          "name": "500ml",
          "sku": "GI-ER-ERDRGI-50"
        }
      ]
    },
    {
      "id": "107120496",
      "name": "Maharani Gin",
      "photos": [
        {
          "id": "41384878",
          "url": "https://www.datocms-assets.com/30257/1644558440-packshot-maharani-gin.png"
        }
      ],
      "variants": [
        {
          "name": "700ml",
          "sku": "GI-RECI-MAGI-70"
        }
      ]
    },
    {
      "id": "5093468",
      "name": "Tropical Old Tom",
      "photos": [
        {
          "id": "2704806",
          "url": "https://www.datocms-assets.com/30257/1601396478-packshot-porters-tropical-old-tom.png"
        }
      ],
      "variants": [
        {
          "name": "700ml",
          "sku": "GI-POGI-TROLTO-70"
        }
      ]
    },
    {
      "id": "17947349",
      "name": "Orchard Gin",
      "photos": [
        {
          "id": "7020201",
          "url": "https://www.datocms-assets.com/30257/1611802994-packshot-porters-orchard-gin.png"
        }
      ],
      "variants": [
        {
          "name": "700ml",
          "sku": "GI-POGI-ORGI-70"
        }
      ]
    },
    {
      "id": "5093448",
      "name": "Modern Classic Gin",
      "photos": [
        {
          "id": "2705562",
          "url": "https://www.datocms-assets.com/30257/1601396909-packshot-porters-modern-classic-gin.png"
        }
      ],
      "variants": [
        {
          "name": "700ml",
          "sku": "GI-POGI-MOCLGI-70"
        }
      ]
    },
    {
      "id": "70774133",
      "name": "Baldoria Orange Wine",
      "photos": [
        {
          "id": "29670724",
          "url": "https://www.datocms-assets.com/30257/1636295750-packshot-baldoria-orange-wine.png"
        }
      ],
      "variants": [
        {
          "name": "750ml",
          "sku": "VBOR0075001"
        }
      ]
    },
    {
      "id": "70572334",
      "name": "Baldoria Verdant",
      "photos": [
        {
          "id": "29546531",
          "url": "https://www.datocms-assets.com/30257/1636147693-packshot-baldoria-verdant.png"
        }
      ],
      "variants": [
        {
          "name": "750ml",
          "sku": "VBVR0075001"
        }
      ]
    },
    {
      "id": "9719454",
      "name": "Test Product",
      "photos": [
        {
          "id": "11459698",
          "url": "https://www.datocms-assets.com/30257/1617316752-packshot-placeholder.png"
        }
      ],
      "variants": [
        {
          "name": "700ml",
          "sku": "TESTSKU"
        }
      ]
    },
    {
      "id": "100818274",
      "name": "Kever 0%",
      "photos": [
        {
          "id": "39106448",
          "url": "https://www.datocms-assets.com/30257/1643168493-packshot-kerver-0-percent.png"
        }
      ],
      "variants": [
        {
          "name": "500ml",
          "sku": "GE-KE-KE0-50"
        }
      ]
    },
    {
      "id": "100817916",
      "name": "Kever Origineel",
      "photos": [
        {
          "id": "39106294",
          "url": "https://www.datocms-assets.com/30257/1643166977-packshot-kerver-origineel.png"
        }
      ],
      "variants": [
        {
          "name": "500ml",
          "sku": "GE-KE-KEOR-50"
        }
      ]
    },
    {
      "id": "14030794",
      "name": "La Jeannette",
      "photos": [
        {
          "id": "5315725",
          "url": "https://www.datocms-assets.com/30257/1608931967-packshot-la-jeanette.png"
        }
      ],
      "variants": [
        {
          "name": "500ml",
          "sku": "GE-LAJE-LAJEGEIM-50"
        }
      ]
    },
    {
      "id": "18509948",
      "name": "RÉtha Oceanic Gin",
      "photos": [
        {
          "id": "7317187",
          "url": "https://www.datocms-assets.com/30257/1612413612-packshot-retha-oceanic-gin.png"
        }
      ],
      "variants": [
        {
          "name": "500ml",
          "sku": "GI-RE-OCGI-50"
        }
      ]
    },
    {
      "id": "59474141",
      "name": "Baldoria Rosé",
      "photos": [
        {
          "id": "24660646",
          "url": "https://www.datocms-assets.com/30257/1632256021-packshot-baldoria-rose.png"
        }
      ],
      "variants": [
        {
          "name": "750",
          "sku": "VBRE0075001"
        }
      ]
    },
    {
      "id": "18616152",
      "name": "Baldoria Dry Rosso",
      "photos": [
        {
          "id": "7316670",
          "url": "https://www.datocms-assets.com/30257/1612411909-packshot-baldoria-dry-rosso.png"
        }
      ],
      "variants": [
        {
          "name": "750ml",
          "sku": "VBDR0075001"
        }
      ]
    },
    {
      "id": "18443459",
      "name": "Baldoria Bianco",
      "photos": [
        {
          "id": "7316665",
          "url": "https://www.datocms-assets.com/30257/1612411280-packshot-baldoria-bianco.png"
        }
      ],
      "variants": [
        {
          "name": "750ml",
          "sku": "VBBI0075001"
        }
      ]
    },
    {
      "id": "8528590",
      "name": "Aperitivo Bitter",
      "photos": [
        {
          "id": "3114561",
          "url": "https://www.datocms-assets.com/30257/1603408096-packshot-argala-aperitivo-bitter.png"
        }
      ],
      "variants": [
        {
          "name": "700ml",
          "sku": "BI-AR-APBI-70"
        }
      ]
    },
    {
      "id": "13898930",
      "name": "Djin no 1: Spirit of Passion",
      "photos": [
        {
          "id": "5264730",
          "url": "https://www.datocms-assets.com/30257/1608669612-packshot-djin-spirits-djin.png"
        }
      ],
      "variants": [
        {
          "name": "500ml",
          "sku": "NOABSP-DJSP-DJ-50"
        }
      ]
    },
    {
      "id": "57016486",
      "name": "Dry Gin",
      "photos": [
        {
          "id": "23883393",
          "url": "https://www.datocms-assets.com/30257/1631573025-stockholms-branneri-dry-gin-packshot.png"
        }
      ],
      "variants": [
        {
          "name": "500ml",
          "sku": "GI-STBR-DRGI-50"
        }
      ]
    },
    {
      "id": "95575962",
      "name": "Vink Whisky Triple Wood",
      "photos": [
        {
          "id": "37499155",
          "url": "https://www.datocms-assets.com/30257/1641965649-packshot-vink-whisky.png"
        }
      ],
      "variants": [
        {
          "name": "700ml",
          "sku": "WH-VI-VIWH-70"
        }
      ]
    },
    {
      "id": "59474050",
      "name": "Baldoria Bitter",
      "photos": [
        {
          "id": "24660602",
          "url": "https://www.datocms-assets.com/30257/1632255810-packshot-baldoria-bitter.png"
        }
      ],
      "variants": [
        {
          "name": "750ml",
          "sku": "VBBT0075001"
        }
      ]
    },
    {
      "id": "18443463",
      "name": "Baldoria Dry",
      "photos": [
        {
          "id": "7316666",
          "url": "https://www.datocms-assets.com/30257/1612411318-packshot-baldoria-dry.png"
        }
      ],
      "variants": [
        {
          "name": "750ml",
          "sku": "VBDY0075001"
        }
      ]
    },
    {
      "id": "18443448",
      "name": "Baldoria Rosso",
      "photos": [
        {
          "id": "7316664",
          "url": "https://www.datocms-assets.com/30257/1612411218-packshot-baldoria-rosso.png"
        }
      ],
      "variants": [
        {
          "name": "750ml",
          "sku": "VBRS0075001"
        }
      ]
    },
    {
      "id": "41037442",
      "name": "ODVI Armagnac",
      "photos": [
        {
          "id": "16747739",
          "url": "https://www.datocms-assets.com/30257/1622240166-packshot-odvi-odvi.png"
        }
      ],
      "variants": [
        {
          "name": "700ml",
          "sku": "AR-OD-OD-70"
        }
      ]
    },
    {
      "id": "61930932",
      "name": "SiWu Dry Gin",
      "photos": [
        {
          "id": "25783495",
          "url": "https://www.datocms-assets.com/30257/1633053167-siwu-dry-gin-packshot.png"
        }
      ],
      "variants": [
        {
          "name": "500ml",
          "sku": "GI-SI-SIPRDR-50"
        }
      ]
    },
    {
      "id": "61931097",
      "name": "SiWu Rose Hip Gin",
      "photos": [
        {
          "id": "25783497",
          "url": "https://www.datocms-assets.com/30257/1633053598-siwu-rose-hip-gin-packshot.png"
        }
      ],
      "variants": [
        {
          "name": "500ml",
          "sku": "GI-SI-SIGIHY-50"
        }
      ]
    },
    {
      "id": "61931527",
      "name": "SiWu Dill Akvavit",
      "photos": [
        {
          "id": "25783540",
          "url": "https://www.datocms-assets.com/30257/1633054646-siwu-dill-akvavit-packshot.png"
        }
      ],
      "variants": [
        {
          "name": "700ml",
          "sku": "AQ-SI-SIPRDI-70"
        }
      ]
    },
    {
      "id": "58031743",
      "name": "Winter Negroni",
      "photos": [
        {
          "id": "24188178",
          "url": "https://www.datocms-assets.com/30257/1631766406-stockholms-branneri-winter-negroni-packshot.png"
        }
      ],
      "variants": [
        {
          "name": "500ml",
          "sku": "RT-STBR-WINE-50"
        }
      ]
    },
    {
      "id": "58031717",
      "name": "Svart",
      "photos": [
        {
          "id": "24188170",
          "url": "https://www.datocms-assets.com/30257/1631766230-stockholms-branneri-svart-packshot.png"
        }
      ],
      "variants": [
        {
          "name": "500ml",
          "sku": "AP-STBR-SV-50"
        }
      ]
    },
    {
      "id": "61931261",
      "name": "SiWu Caraway Akvavit",
      "photos": [
        {
          "id": "25783510",
          "url": "https://www.datocms-assets.com/30257/1633054217-siwu-caraway-akvavit-packshot.png"
        }
      ],
      "variants": [
        {
          "name": "700ml",
          "sku": "AQ-SI-SIPRAK-70"
        }
      ]
    },
    {
      "id": "57580409",
      "name": "Stockholms Akvavit",
      "photos": [
        {
          "id": "24063012",
          "url": "https://www.datocms-assets.com/30257/1631648313-stockholms-branneri-akvavit-packshot.png"
        }
      ],
      "variants": [
        {
          "name": "500ml",
          "sku": "AQ-STBR-AK-50"
        }
      ]
    },
    {
      "id": "57580380",
      "name": "Pink Gin",
      "photos": [
        {
          "id": "24062964",
          "url": "https://www.datocms-assets.com/30257/1631647721-stockholms-branneri-pink-gin-packshot.png"
        }
      ],
      "variants": [
        {
          "name": "500ml",
          "sku": "GI-STBR-PIGI-50"
        }
      ]
    },
    {
      "id": "57580818",
      "name": "Röd",
      "photos": [
        {
          "id": "24063318",
          "url": "https://www.datocms-assets.com/30257/1631648801-stockholms-branneri-rod-packshot.png"
        }
      ],
      "variants": [
        {
          "name": "500ml",
          "sku": "AP-STBR-RO-50"
        }
      ]
    },
    {
      "id": "8615364",
      "name": "Figli dei Fiori Elderflower",
      "photos": [
        {
          "id": "3114563",
          "url": "https://www.datocms-assets.com/30257/1603408137-packshot-argala-figlie-dei-fiori-elderflowers.png"
        }
      ],
      "variants": [
        {
          "name": "500ml",
          "sku": "LI-AR-FIFIEL-50"
        }
      ]
    },
    {
      "id": "10549911",
      "name": "Erika Gin de Printemps",
      "photos": [
        {
          "id": "4031290",
          "url": "https://www.datocms-assets.com/30257/1605227869-packshot-erika-gin-de-printemps.png"
        }
      ],
      "variants": [
        {
          "name": "500ml",
          "sku": "GI-ER-ERGIPR-50"
        }
      ]
    },
    {
      "id": "10549847",
      "name": "Erika Old Tom Gin",
      "photos": [
        {
          "id": "4031273",
          "url": "https://www.datocms-assets.com/30257/1605226561-packshot-erika-old-tom-gin.png"
        }
      ],
      "variants": [
        {
          "name": "500ml",
          "sku": "GI-ER-EROLTO-50"
        }
      ]
    },
    {
      "id": "10597769",
      "name": "Koch Ensamble",
      "photos": [
        {
          "id": "4082327",
          "url": "https://www.datocms-assets.com/30257/1605288391-packshot-koch-ensamble.png"
        }
      ],
      "variants": [
        {
          "name": "700ml",
          "sku": "ME-KO-KOEN-70"
        }
      ]
    },
    {
      "id": "10380744",
      "name": "Tequila Vecindad",
      "photos": [
        {
          "id": "4003755",
          "url": "https://www.datocms-assets.com/30257/1605142393-packshot-tequila-vecindad.png"
        }
      ],
      "variants": [
        {
          "name": "700ml",
          "sku": "TE-VE-TEVE-70"
        }
      ]
    },
    {
      "id": "10534285",
      "name": "Wild Fermented Rum",
      "photos": [
        {
          "id": "4030412",
          "url": "https://www.datocms-assets.com/30257/1605203105-packshot-el-destilado-rum.png"
        }
      ],
      "variants": [
        {
          "name": "700ml",
          "sku": "RU-ELDE-ELDERU-70"
        }
      ]
    },
    {
      "id": "9863340",
      "name": "Umami Gin",
      "photos": [
        {
          "id": "3807578",
          "url": "https://www.datocms-assets.com/30257/1604440568-packshot-audemus-umami-gin.png"
        }
      ],
      "variants": [
        {
          "name": "500ml",
          "sku": "GI-AUSP-UMGI-50"
        }
      ]
    },
    {
      "id": "51305229",
      "name": "Silent Pool Gin",
      "photos": [
        {
          "id": "21196416",
          "url": "https://www.datocms-assets.com/30257/1628398471-packshot-silent-pool-silent-pool-gin.png"
        }
      ],
      "variants": [
        {
          "name": "700ml",
          "sku": "GI-SIPO-SIPOGI-70"
        }
      ]
    },
    {
      "id": "41665572",
      "name": "Armagnac Castarède Hors d’Age",
      "photos": [
        {
          "id": "17066651",
          "url": "https://www.datocms-assets.com/30257/1622921334-packshot-armagnac-castarede-hors-d-age.png"
        }
      ],
      "variants": [
        {
          "name": "700ml",
          "sku": "AR-ARCA-HOAG-70"
        }
      ]
    },
    {
      "id": "11676151",
      "name": "Vache Salted Caramel",
      "photos": [
        {
          "id": "4519892",
          "url": "https://www.datocms-assets.com/30257/1606861744-packshot-la-capricieuse-vache-caramel-fleur-de-sel.png"
        }
      ],
      "variants": [
        {
          "name": "500ml",
          "sku": "LI-LACA-VACAFLDESE-50"
        }
      ]
    },
    {
      "id": "8376302",
      "name": "Yaguara Blue",
      "photos": [
        {
          "id": "3055224",
          "url": "https://www.datocms-assets.com/30257/1603215056-packshot-yaguara-cachaca-blue.png"
        }
      ],
      "variants": [
        {
          "name": "700ml",
          "sku": "CA-YA-YABL-70"
        }
      ]
    },
    {
      "id": "41665558",
      "name": "Armagnac Castarède VSOP",
      "photos": [
        {
          "id": "17066646",
          "url": "https://www.datocms-assets.com/30257/1622920770-packshot-armagnac-castarede-vsop.png"
        }
      ],
      "variants": [
        {
          "name": "700ml",
          "sku": "AR-ARCA-VS-70"
        }
      ]
    },
    {
      "id": "35976024",
      "name": "Borderies Mizunara",
      "photos": [
        {
          "id": "14959312",
          "url": "https://www.datocms-assets.com/30257/1619990148-packshot-cognac-park-borderies-mizunara.png"
        }
      ],
      "variants": [
        {
          "name": "700ml",
          "sku": "CO-COPA-BOMI-70"
        }
      ]
    },
    {
      "id": "40441462",
      "name": "Eau de Vie Poire Williams",
      "photos": [
        {
          "id": "16490412",
          "url": "https://www.datocms-assets.com/30257/1621834962-packshot-distillerie-ogier-poire-williams.png"
        }
      ],
      "variants": [
        {
          "name": "700ml",
          "sku": "EADEVI-DIOG-POWI-70"
        }
      ]
    },
    {
      "id": "7314951",
      "name": "Helena",
      "photos": [
        {
          "id": "2705573",
          "url": "https://www.datocms-assets.com/30257/1601397353-packshot-empirical-spirits-helena.png"
        }
      ],
      "variants": [
        {
          "name": "500ml",
          "sku": "SP-EMSP-HE-50"
        }
      ]
    },
    {
      "id": "11982525",
      "name": "Rendez-Vous",
      "photos": [
        {
          "id": "4586712",
          "url": "https://www.datocms-assets.com/30257/1607042199-packshot-lehmann-rendez-vous.png"
        }
      ],
      "variants": [
        {
          "name": "700ml",
          "sku": "WH-LE-RE-70"
        }
      ]
    },
    {
      "id": "10597704",
      "name": "Koch Espadin",
      "photos": [
        {
          "id": "4082290",
          "url": "https://www.datocms-assets.com/30257/1605287126-packshot-koch-espadin.png"
        }
      ],
      "variants": [
        {
          "name": "700ml",
          "sku": "ME-KO-KOES-70"
        }
      ]
    },
    {
      "id": "7575897",
      "name": "The Plum, I Suppose",
      "photos": [
        {
          "id": "2706089",
          "url": "https://www.datocms-assets.com/30257/1601414607-packshot-empirical-spirits-the-plum-i-suppose.png"
        }
      ],
      "variants": [
        {
          "name": "500ml",
          "sku": "SP-EMSP-THPLISU-50"
        }
      ]
    },
    {
      "id": "19439310",
      "name": "Brazil Epris 8 ans",
      "photos": [
        {
          "id": "7485568",
          "url": "https://www.datocms-assets.com/30257/1612733777-packshot-compagnie-des-indes-brazil-8-ans.png"
        }
      ],
      "variants": [
        {
          "name": "700ml",
          "sku": "RU-CODEIN-BREP8AN-70"
        }
      ]
    },
    {
      "id": "19439351",
      "name": "Brazil Epris Brut de Fut",
      "photos": [
        {
          "id": "7485654",
          "url": "https://www.datocms-assets.com/30257/1612734169-packshot-compagnie-des-indes-brazil-8-ans-cask-strength.png"
        }
      ],
      "variants": [
        {
          "name": "700ml",
          "sku": "RU-CODEIN-BREPBRDEFU-70"
        }
      ]
    },
    {
      "id": "17929216",
      "name": "Vanille & Noisette",
      "photos": [
        {
          "id": "4519839",
          "url": "https://www.datocms-assets.com/30257/1606861297-packshot-la-capricieuse-vanille-noisette.png"
        }
      ],
      "variants": [
        {
          "name": "500ml",
          "sku": "LI-LACA-VAVANO-50"
        }
      ]
    },
    {
      "id": "19455949",
      "name": "Trinidad Ten Cane 11 Ans",
      "photos": [
        {
          "id": "7489287",
          "url": "https://www.datocms-assets.com/30257/1612737250-packshot-compagnie-des-indes-trinidad-ten-cane.png"
        }
      ],
      "variants": [
        {
          "name": "700ml",
          "sku": "RU-CODEIN-TRTECA11AN-70"
        }
      ]
    },
    {
      "id": "19455965",
      "name": "Trinidad T.D.L. 13 Ans",
      "photos": [
        {
          "id": "7489296",
          "url": "https://www.datocms-assets.com/30257/1612738168-packshot-compagnie-des-indes-trinidad-13-ans.png"
        }
      ],
      "variants": [
        {
          "name": "700ml",
          "sku": "RU-CODEIN-TRTD-70"
        }
      ]
    },
    {
      "id": "11696996",
      "name": "Chevre Chestnut",
      "photos": [
        {
          "id": "4593046",
          "url": "https://www.datocms-assets.com/30257/1607050795-packshot-la-capricieuse-chevre-chataignes.png"
        }
      ],
      "variants": [
        {
          "name": "500ml",
          "sku": "LI-LACA-CHCH-50"
        }
      ]
    },
    {
      "id": "8409158",
      "name": "Principe de los Apóstoles",
      "photos": [
        {
          "id": "2999502",
          "url": "https://www.datocms-assets.com/30257/1603044007-packshot-apostoles-apostoles-gin.png"
        }
      ],
      "variants": [
        {
          "name": "700ml",
          "sku": "GI-PRDELOAP-PRDELOAPGI-70"
        }
      ]
    },
    {
      "id": "33982268",
      "name": "Pur Malt Macvin",
      "photos": [
        {
          "id": "14602122",
          "url": "https://www.datocms-assets.com/30257/1619634468-packshot-bm-signature-pur-malt-macvin.png"
        }
      ],
      "variants": [
        {
          "name": "700ml",
          "sku": "WH-BMSIWH-PUMAMA-70"
        }
      ]
    },
    {
      "id": "9900557",
      "name": "Pink Pepper Dry Gin",
      "photos": [
        {
          "id": "3825244",
          "url": "https://www.datocms-assets.com/30257/1604512829-packshot-audemus-pink-pepper-dry-gin.png"
        }
      ],
      "variants": [
        {
          "name": "700ml",
          "sku": "GI-AUSP-PIPEDRGI-70"
        }
      ]
    },
    {
      "id": "10602461",
      "name": "Cuish Tepextate",
      "photos": [
        {
          "id": "4084020",
          "url": "https://www.datocms-assets.com/30257/1605298487-packshot-cuish-tepeztate.png"
        }
      ],
      "variants": [
        {
          "name": "700ml",
          "sku": "DE-CU-CUTE-70"
        }
      ]
    },
    {
      "id": "35979002",
      "name": "Borderies Mizunara Single Cask 2006",
      "photos": [
        {
          "id": "14965856",
          "url": "https://www.datocms-assets.com/30257/1620000681-packshot-cognac-park-single-cask-borderies-mizunara-2006.png"
        }
      ],
      "variants": [
        {
          "name": "700ml",
          "sku": "CO-COPA-SICABOMI06-70"
        }
      ]
    },
    {
      "id": "19438987",
      "name": "Caraïbes",
      "photos": [
        {
          "id": "7485338",
          "url": "https://www.datocms-assets.com/30257/1612732516-packshot-compagnie-des-indes-caraibes.png"
        }
      ],
      "variants": [
        {
          "name": "700ml",
          "sku": "RU-CODEIN-CA-70"
        }
      ]
    },
    {
      "id": "18509957",
      "name": "RÉtha Vodka la Blanche",
      "photos": [
        {
          "id": "7317188",
          "url": "https://www.datocms-assets.com/30257/1612413637-packshot-retha-vodka-la-blanche.png"
        }
      ],
      "variants": [
        {
          "name": "500ml",
          "sku": "VO-RE-VOLABL-50"
        }
      ]
    },
    {
      "id": "24375802",
      "name": "Le Whisky des Français",
      "photos": [
        {
          "id": "10237249",
          "url": "https://www.datocms-assets.com/30257/1615563283-packshot-le-whisky-des-francais-lwdf.png"
        }
      ],
      "variants": [
        {
          "name": "500ml",
          "sku": "WH-LEWHDEFR-LEWHDEFR-50"
        }
      ]
    },
    {
      "id": "33425665",
      "name": "Crème de Fleur de Sureau",
      "photos": [
        {
          "id": "13979774",
          "url": "https://www.datocms-assets.com/30257/1619113608-packshot-sathenay-liqueur-de-fleur-de-sureau.png"
        }
      ],
      "variants": [
        {
          "name": "700ml",
          "sku": "LI-SA-CRDEFLDESU-70"
        }
      ]
    },
    {
      "id": "13898199",
      "name": "XO Iris Poivré",
      "photos": [
        {
          "id": "5264335",
          "url": "https://www.datocms-assets.com/30257/1608660454-packshot-fanny-fougerat-iris-poivre.png"
        }
      ],
      "variants": [
        {
          "name": "700ml",
          "sku": "CO-FAFO-XOIRPO-70"
        }
      ]
    },
    {
      "id": "13898166",
      "name": "Laurier d’Apollon",
      "photos": [
        {
          "id": "5264307",
          "url": "https://www.datocms-assets.com/30257/1608659811-packshot-fanny-fougerat-lauriere-d-apollon.png"
        }
      ],
      "variants": [
        {
          "name": "700ml",
          "sku": "CO-FAFO-LAAP-70"
        }
      ]
    },
    {
      "id": "19439241",
      "name": "Guyana 12 ans",
      "photos": [
        {
          "id": "7485522",
          "url": "https://www.datocms-assets.com/30257/1612733322-packshot-compagnie-des-indes-guyana-madeira.png"
        }
      ],
      "variants": [
        {
          "name": "700ml",
          "sku": "RU-CODEIN-GU12ANFIMA-70"
        }
      ]
    },
    {
      "id": "8390245",
      "name": "Caperitif",
      "photos": [
        {
          "id": "3693229",
          "url": "https://www.datocms-assets.com/30257/1604069271-packshot-caperitif-caperitif.png"
        }
      ],
      "variants": [
        {
          "name": "700ml",
          "sku": "VE-CA-CA-70"
        }
      ]
    },
    {
      "id": "7575883",
      "name": "Fuck Trump...",
      "photos": [
        {
          "id": "2706035",
          "url": "https://www.datocms-assets.com/30257/1601412863-packshot-empirical-spirits-fuck-trump.png"
        }
      ],
      "variants": [
        {
          "name": "500ml",
          "sku": "SP-EMSP-FUTR-50"
        }
      ]
    },
    {
      "id": "33985627",
      "name": "Pur Malt Vin Jaune 9 Ans",
      "photos": [
        {
          "id": "14371399",
          "url": "https://www.datocms-assets.com/30257/1619480453-packshot-pur-malt-vin-jaune-9-ans.png"
        }
      ],
      "variants": [
        {
          "name": "700ml",
          "sku": "WH-BMSIWH-PUMAVIJAAN-70"
        }
      ]
    },
    {
      "id": "10752137",
      "name": "Quebranta",
      "photos": [
        {
          "id": "4135725",
          "url": "https://www.datocms-assets.com/30257/1605655337-packshot-la-caravedo.png"
        }
      ],
      "variants": [
        {
          "name": "700",
          "sku": "PI-LACA-QU-70"
        }
      ]
    },
    {
      "id": "11982533",
      "name": "Gewurztraminer Marc",
      "photos": [
        {
          "id": "4586721",
          "url": "https://www.datocms-assets.com/30257/1607042560-packshot-lehmann-marc-de-gewurtzraminer-aoc.png"
        }
      ],
      "variants": [
        {
          "name": "700ml",
          "sku": "EADEVI-LE-MADEGEAO-70"
        }
      ]
    },
    {
      "id": "49378734",
      "name": "Menéres LBV 2014",
      "photos": [
        {
          "id": "20219970",
          "url": "https://www.datocms-assets.com/30257/1627251516-packshot-meneres-port-lbv-2014.png"
        }
      ],
      "variants": [
        {
          "name": "750ML",
          "sku": "PO-ME-LB14-75"
        }
      ]
    },
    {
      "id": "19439215",
      "name": "Latino",
      "photos": [
        {
          "id": "7485393",
          "url": "https://www.datocms-assets.com/30257/1612733056-packshot-compagnie-des-indes-latino.png"
        }
      ],
      "variants": [
        {
          "name": "700ml",
          "sku": "RU-CODEIN-LA-70"
        }
      ]
    },
    {
      "id": "49399083",
      "name": "Menéres Tawny Port 10 Years",
      "photos": [
        {
          "id": "20227404",
          "url": "https://www.datocms-assets.com/30257/1627259344-packshot-meneres-port-10-ans.png"
        }
      ],
      "variants": [
        {
          "name": "750ml",
          "sku": "PO-ME-TAPO10AN-75"
        }
      ]
    },
    {
      "id": "49399103",
      "name": "Menéres Tawny Port 20 Years",
      "photos": [
        {
          "id": "20235544",
          "url": "https://www.datocms-assets.com/30257/1627261875-packshot-meneres-port-20-ans.png"
        }
      ],
      "variants": [
        {
          "name": "750ml",
          "sku": "PO-ME-TAPO20AN-75"
        }
      ]
    },
    {
      "id": "10528753",
      "name": "Lalocura Tobalá",
      "photos": [
        {
          "id": "4029246",
          "url": "https://www.datocms-assets.com/30257/1605196839-packshot-lalocuar-tobala.png"
        }
      ],
      "variants": [
        {
          "name": "700ml",
          "sku": "DE-LA-LATO-70"
        }
      ]
    },
    {
      "id": "10002673",
      "name": "Covert Liqueur",
      "photos": [
        {
          "id": "3860438",
          "url": "https://www.datocms-assets.com/30257/1604698320-packshot-audemus-covert-liquer.png"
        }
      ],
      "variants": [
        {
          "name": "500ml",
          "sku": "LI-AUSP-COLI-50"
        }
      ]
    },
    {
      "id": "10380573",
      "name": "El Viejo",
      "photos": [
        {
          "id": "4003591",
          "url": "https://www.datocms-assets.com/30257/1605135817-packshot-mezcal-union-el-viejo.png"
        }
      ],
      "variants": [
        {
          "name": "700ml",
          "sku": "ME-MEUN-ELVI-70"
        }
      ]
    },
    {
      "id": "23565967",
      "name": "Mr. Gaston",
      "photos": [
        {
          "id": "9815461",
          "url": "https://www.datocms-assets.com/30257/1615077350-packshot-mr-gaston-brandy.png"
        }
      ],
      "variants": [
        {
          "name": "700ml",
          "sku": "BR-MRGA-MRGABR-70"
        }
      ]
    },
    {
      "id": "35978774",
      "name": "Borderies Mizunara 10 Ans",
      "photos": [
        {
          "id": "14961061",
          "url": "https://www.datocms-assets.com/30257/1619999657-packshot-cognac-park-borderies-mizunara-10ans.png"
        }
      ],
      "variants": [
        {
          "name": "700ml",
          "sku": "CO-COPA-BOMI10AN-70"
        }
      ]
    },
    {
      "id": "7574414",
      "name": "Ayuuk",
      "photos": [
        {
          "id": "2705583",
          "url": "https://www.datocms-assets.com/30257/1601398061-packshot-empirical-spirits-ayuuk.png"
        }
      ],
      "variants": [
        {
          "name": "500ml",
          "sku": "SP-EMSP-AY-50"
        }
      ]
    },
    {
      "id": "10380462",
      "name": "Unión Uno",
      "photos": [
        {
          "id": "4003540",
          "url": "https://www.datocms-assets.com/30257/1605134624-packshot-mezcal-union-el-joven.png"
        }
      ],
      "variants": [
        {
          "name": "700ml",
          "sku": "ME-MEUN-UNUN-70"
        }
      ]
    },
    {
      "id": "33985841",
      "name": "Single Cask Vin de Paille 2006",
      "photos": [
        {
          "id": "14371418",
          "url": "https://www.datocms-assets.com/30257/1619480497-packshot-bm-signature-single-cask-vin-de-paille-2006.png"
        }
      ],
      "variants": [
        {
          "name": "700ml",
          "sku": "WH-BMSIWH-SICAVIDEPA06-70"
        }
      ]
    },
    {
      "id": "9722885",
      "name": "Pink Pepper Gin",
      "photos": [
        {
          "id": "3719928",
          "url": "https://www.datocms-assets.com/30257/1604314664-packshot-audemus-pink-pepper-gin.png"
        }
      ],
      "variants": [
        {
          "name": "700ml",
          "sku": "GI-AUSP-PIPEGI-70"
        }
      ]
    },
    {
      "id": "10597607",
      "name": "Koch Tobalá",
      "photos": [
        {
          "id": "4082213",
          "url": "https://www.datocms-assets.com/30257/1605285710-packshot-koch-tobala.png"
        }
      ],
      "variants": [
        {
          "name": "700ml",
          "sku": "ME-KO-KOTO-70"
        }
      ]
    },
    {
      "id": "11981776",
      "name": "C’est La Vie",
      "photos": [
        {
          "id": "4585723",
          "url": "https://www.datocms-assets.com/30257/1607030694-packshot-lehmann-cest-la-vie.png"
        }
      ],
      "variants": [
        {
          "name": "700ml",
          "sku": "WH-LE-ESLAVI-70"
        }
      ]
    },
    {
      "id": "8376597",
      "name": "Yaguara Ouro",
      "photos": [
        {
          "id": "3055225",
          "url": "https://www.datocms-assets.com/30257/1603215087-packshot-yaguara-cachaca-ouro.png"
        }
      ],
      "variants": [
        {
          "name": "700ml",
          "sku": "CA-YA-YAOU-70"
        }
      ]
    },
    {
      "id": "33413519",
      "name": "Crème de Cassis",
      "photos": [
        {
          "id": "13977702",
          "url": "https://www.datocms-assets.com/30257/1619112451-packshot-sathenay-creme-de-cassis.png"
        }
      ],
      "variants": [
        {
          "name": "700ml",
          "sku": "LI-SA-CRDECA-70"
        }
      ]
    },
    {
      "id": "13898217",
      "name": "XO Cèdre Blanc",
      "photos": [
        {
          "id": "5264342",
          "url": "https://www.datocms-assets.com/30257/1608660840-packshot-fanny-fougerat-cedre-blanc.png"
        }
      ],
      "variants": [
        {
          "name": "700ml",
          "sku": "CO-FAFO-XODRBL-70"
        }
      ]
    },
    {
      "id": "33413663",
      "name": "Crème de Pêche de Vigne",
      "photos": [
        {
          "id": "13979633",
          "url": "https://www.datocms-assets.com/30257/1619112972-packshot-sathenay-creme-de-peche-de-vigne.png"
        }
      ],
      "variants": [
        {
          "name": "700ml",
          "sku": "LI-SA-CRDECH-70"
        }
      ]
    },
    {
      "id": "16881983",
      "name": "White Spiced Rum",
      "photos": [
        {
          "id": "6557807",
          "url": "https://www.datocms-assets.com/30257/1611450094-packshot-beach-house-rum-beach-house-white.png"
        }
      ],
      "variants": [
        {
          "name": "700ml",
          "sku": "RU-BEHORU-BEHOWH-70"
        }
      ]
    },
    {
      "id": "8376641",
      "name": "Yaguara Branca",
      "photos": [
        {
          "id": "3055226",
          "url": "https://www.datocms-assets.com/30257/1603215122-packshot-yaguara-cachaca-branca.png"
        }
      ],
      "variants": [
        {
          "name": "700ml",
          "sku": "CA-YA-YABR-70"
        }
      ]
    },
    {
      "id": "13846303",
      "name": "Vsop Petite Cigüe",
      "photos": [
        {
          "id": "5243789",
          "url": "https://www.datocms-assets.com/30257/1608614933-packshot-fanny-fougerat-vsop-petite-cigue.png"
        }
      ],
      "variants": [
        {
          "name": "700ml",
          "sku": "AR-ARCA-VS-70"
        }
      ]
    },
    {
      "id": "12081147",
      "name": "La Philosophe Vodka",
      "photos": [
        {
          "id": "4635930",
          "url": "https://www.datocms-assets.com/30257/1607216951-packshot-la-philosophe.png"
        }
      ],
      "variants": [
        {
          "name": "700ml",
          "sku": "VO-LAPH-LAPHVO-70"
        }
      ]
    },
    {
      "id": "16182710",
      "name": "Highland Journey",
      "photos": [
        {
          "id": "6292173",
          "url": "https://www.datocms-assets.com/30257/1610759194-packshot-hunter-laing-highland-journey.png"
        }
      ],
      "variants": [
        {
          "name": "700ml",
          "sku": "WH-HULA-HIJO-70"
        }
      ]
    },
    {
      "id": "35979139",
      "name": "Borderies Mizunara Single Cask 2004",
      "photos": [
        {
          "id": "14965932",
          "url": "https://www.datocms-assets.com/30257/1620001165-packshot-cognac-park-single-cask-borderies-mizunara-2006.png"
        }
      ],
      "variants": [
        {
          "name": "700ml",
          "sku": "CO-COPA-SICABOMI04-70"
        }
      ]
    },
    {
      "id": "10375423",
      "name": "Neta Bicuixe",
      "photos": [
        {
          "id": "4003131",
          "url": "https://www.datocms-assets.com/30257/1605120083-packshot-neta-neta-bicuixe.png"
        }
      ],
      "variants": [
        {
          "name": "700ml",
          "sku": "DE-NE-NEBI-70"
        }
      ]
    },
    {
      "id": "31993669",
      "name": "Glasshouse Whisky",
      "photos": [
        {
          "id": "13471430",
          "url": "https://www.datocms-assets.com/30257/1618682011-packshot-glasshouse-whisky.png"
        }
      ],
      "variants": [
        {
          "name": "700ml",
          "sku": "WH-GL-GLWH-70"
        }
      ]
    },
    {
      "id": "7575986",
      "name": "Pastis Artigianale",
      "photos": [
        {
          "id": "2707912",
          "url": "https://www.datocms-assets.com/30257/1601459609-packshot-argala-pastis.png"
        }
      ],
      "variants": [
        {
          "name": "700ml",
          "sku": "PA-AR-PAAR-70"
        }
      ]
    },
    {
      "id": "27384195",
      "name": "Barrel-Aged Cachaça",
      "photos": [
        {
          "id": "12925067",
          "url": "https://www.datocms-assets.com/30257/1618257063-packshot-novo-fogo-barrel-aged-cachaca.png"
        }
      ],
      "variants": [
        {
          "name": "700ml",
          "sku": "CA-NOFO-BACA-70"
        }
      ]
    },
    {
      "id": "27384284",
      "name": "Tanager",
      "photos": [
        {
          "id": "12925113",
          "url": "https://www.datocms-assets.com/30257/1618257658-packshot-novo-fogo-tanager.png"
        }
      ],
      "variants": [
        {
          "name": "700ml",
          "sku": "CA-NOFO-TA-70"
        }
      ]
    },
    {
      "id": "27384204",
      "name": "Chameleon",
      "photos": [
        {
          "id": "12925107",
          "url": "https://www.datocms-assets.com/30257/1618257612-packshot-novo-fogo-chameleon.png"
        }
      ],
      "variants": [
        {
          "name": "700ml",
          "sku": "CA-NOFO-CH-70"
        }
      ]
    },
    {
      "id": "27377380",
      "name": "Silver Cachaça",
      "photos": [
        {
          "id": "12925066",
          "url": "https://www.datocms-assets.com/30257/1618257016-packshot-novo-fogo-silver-cachca.png"
        }
      ],
      "variants": [
        {
          "name": "700ml",
          "sku": "CA-NOFO-SICA-70"
        }
      ]
    },
    {
      "id": "39058369",
      "name": "Erika Vodka Polka",
      "photos": [
        {
          "id": "15889848",
          "url": "https://www.datocms-assets.com/30257/1620881235-packshot-erika-vodka-polka.png"
        }
      ],
      "variants": [
        {
          "name": "500ml",
          "sku": "VO-ER-VOPO-50"
        }
      ]
    },
    {
      "id": "10549866",
      "name": "Erika Navy Strength",
      "photos": [
        {
          "id": "4031279",
          "url": "https://www.datocms-assets.com/30257/1605227060-packshot-erika-navy-strength.png"
        }
      ],
      "variants": [
        {
          "name": "500ml",
          "sku": "GI-ER-ERNAST-50"
        }
      ]
    },
    {
      "id": "11981911",
      "name": "Coup de Foudre",
      "photos": [
        {
          "id": "4585827",
          "url": "https://www.datocms-assets.com/30257/1607031406-packshot-lehmann-coup-de-foudre.png"
        }
      ],
      "variants": [
        {
          "name": "700ml",
          "sku": "WH-LE-CODEFO-70"
        }
      ]
    }
  ]
}
